bellows/__init__.py
bellows/commands.py
bellows/exception.py
bellows/ezsp.py
bellows/multicast.py
bellows/thread.py
bellows/uart.py
bellows/cli/__init__.py
bellows/cli/application.py
bellows/cli/dump.py
bellows/cli/main.py
bellows/cli/ncp.py
bellows/cli/network.py
bellows/cli/opts.py
bellows/cli/util.py
bellows/types/__init__.py
bellows/types/basic.py
bellows/types/named.py
bellows/types/struct.py
bellows/zigbee/__init__.py
bellows/zigbee/application.py
bellows/zigbee/util.py
bellows_homeassistant-0.15.2.dist-info/COPYING
bellows_homeassistant-0.15.2.dist-info/LICENSE
bellows_homeassistant-0.15.2.dist-info/METADATA
bellows_homeassistant-0.15.2.dist-info/WHEEL
bellows_homeassistant-0.15.2.dist-info/dependency_links.txt
bellows_homeassistant-0.15.2.dist-info/entry_points.txt
bellows_homeassistant-0.15.2.dist-info/top_level.txt
bellows_homeassistant-0.15.2.dist-info/RECORD
