Metadata-Version: 2.1
Name: bellows-homeassistant
Version: 0.15.2
Summary: Library implementing EZSP
Home-page: http://github.com/zigpy/bellows
Author: Russell Cloran
Author-email: rcloran@gmail.com
License: GPL-3.0
Platform: UNKNOWN
Requires-Dist: Click
Requires-Dist: click-log (==0.2.0)
Requires-Dist: pure-pcapy3 (==1.0.1)
Requires-Dist: pyserial-asyncio
Requires-Dist: voluptuous
Requires-Dist: zigpy-homeassistant (>=0.17.0)
